marge/__init__.py
marge/__main__.py
marge/app.py
marge/approvals.py
marge/batch_job.py
marge/bot.py
marge/branch.py
marge/commit.py
marge/git.py
marge/gitlab.py
marge/hooks.py
marge/interval.py
marge/job.py
marge/keepcommitters.py
marge/merge_request.py
marge/pipeline.py
marge/project.py
marge/single_merge_job.py
marge/store.py
marge/trailerfilter.py
marge/user.py
marge_bot-1.0.0.dist-info/METADATA
marge_bot-1.0.0.dist-info/WHEEL
marge_bot-1.0.0.dist-info/entry_points.txt
marge_bot-1.0.0.dist-info/licenses/LICENSE
marge_bot-1.0.0.dist-info/RECORD
