Metadata-Version: 2.4
Name: marge-bot
Version: 1.0.0
Summary: marge-bot is a merge bot for GitLab.
Author-email: Smarkets Infrastructure <infrastructure@smarkets.com>
Maintainer-email: Marge-bot Community <marge-bot@proton.me>
License-Expression: BSD-3-Clause
License-File: LICENSE
Keywords: gitlab,merge request,merge train
Requires-Python: >=3.10.0
Requires-Dist: configargparse>=1.7.1
Requires-Dist: python-gitlab>=7.0.0
Requires-Dist: pyyaml>=6.0.3
Requires-Dist: requests>=2.32.5
